<annotation>
	<folder>BD2</folder>
	<filename>112.JPG</filename>
	<path>F:\Sieci\BD2\112.JPG</path>
	<source>
		<database>Unknown</database>
	</source>
	<size>
		<width>939</width>
		<height>768</height>
		<depth>3</depth>
	</size>
	<segmented>0</segmented>
	<object>
		<name>church</name>
		<pose>Unspecified</pose>
		<truncated>0</truncated>
		<difficult>0</difficult>
		<bndbox>
			<xmin>4</xmin>
			<ymin>99</ymin>
			<xmax>336</xmax>
			<ymax>290</ymax>
		</bndbox>
	</object>
	<object>
		<name>block of flats</name>
		<pose>Unspecified</pose>
		<truncated>0</truncated>
		<difficult>0</difficult>
		<bndbox>
			<xmin>23</xmin>
			<ymin>323</ymin>
			<xmax>277</xmax>
			<ymax>414</ymax>
		</bndbox>
	</object>
	<object>
		<name>block of flats</name>
		<pose>Unspecified</pose>
		<truncated>1</truncated>
		<difficult>0</difficult>
		<bndbox>
			<xmin>5</xmin>
			<ymin>423</ymin>
			<xmax>385</xmax>
			<ymax>768</ymax>
		</bndbox>
	</object>
	<object>
		<name>block of flats</name>
		<pose>Unspecified</pose>
		<truncated>0</truncated>
		<difficult>0</difficult>
		<bndbox>
			<xmin>405</xmin>
			<ymin>433</ymin>
			<xmax>869</xmax>
			<ymax>754</ymax>
		</bndbox>
	</object>
	<object>
		<name>block of flats</name>
		<pose>Unspecified</pose>
		<truncated>0</truncated>
		<difficult>0</difficult>
		<bndbox>
			<xmin>403</xmin>
			<ymin>23</ymin>
			<xmax>860</xmax>
			<ymax>405</ymax>
		</bndbox>
	</object>
</annotation>
