<annotation>
	<folder>BD2</folder>
	<filename>220.JPG</filename>
	<path>F:\Sieci\BD2\220.JPG</path>
	<source>
		<database>Unknown</database>
	</source>
	<size>
		<width>550</width>
		<height>796</height>
		<depth>3</depth>
	</size>
	<segmented>0</segmented>
	<object>
		<name>block of flats</name>
		<pose>Unspecified</pose>
		<truncated>0</truncated>
		<difficult>0</difficult>
		<bndbox>
			<xmin>15</xmin>
			<ymin>530</ymin>
			<xmax>493</xmax>
			<ymax>681</ymax>
		</bndbox>
	</object>
	<object>
		<name>block of flats</name>
		<pose>Unspecified</pose>
		<truncated>0</truncated>
		<difficult>0</difficult>
		<bndbox>
			<xmin>451</xmin>
			<ymin>638</ymin>
			<xmax>526</xmax>
			<ymax>774</ymax>
		</bndbox>
	</object>
	<object>
		<name>block of flats</name>
		<pose>Unspecified</pose>
		<truncated>0</truncated>
		<difficult>0</difficult>
		<bndbox>
			<xmin>337</xmin>
			<ymin>651</ymin>
			<xmax>406</xmax>
			<ymax>768</ymax>
		</bndbox>
	</object>
	<object>
		<name>garage</name>
		<pose>Unspecified</pose>
		<truncated>1</truncated>
		<difficult>0</difficult>
		<bndbox>
			<xmin>269</xmin>
			<ymin>653</ymin>
			<xmax>307</xmax>
			<ymax>796</ymax>
		</bndbox>
	</object>
	<object>
		<name>shopping_center</name>
		<pose>Unspecified</pose>
		<truncated>0</truncated>
		<difficult>0</difficult>
		<bndbox>
			<xmin>98</xmin>
			<ymin>42</ymin>
			<xmax>491</xmax>
			<ymax>499</ymax>
		</bndbox>
	</object>
</annotation>
