<annotation>
	<folder>BD2</folder>
	<filename>298.JPG</filename>
	<path>F:\Sieci\BD2\298.JPG</path>
	<source>
		<database>Unknown</database>
	</source>
	<size>
		<width>543</width>
		<height>766</height>
		<depth>3</depth>
	</size>
	<segmented>0</segmented>
	<object>
		<name>shopping_center</name>
		<pose>Unspecified</pose>
		<truncated>0</truncated>
		<difficult>0</difficult>
		<bndbox>
			<xmin>70</xmin>
			<ymin>61</ymin>
			<xmax>324</xmax>
			<ymax>247</ymax>
		</bndbox>
	</object>
	<object>
		<name>shopping_center</name>
		<pose>Unspecified</pose>
		<truncated>0</truncated>
		<difficult>0</difficult>
		<bndbox>
			<xmin>81</xmin>
			<ymin>505</ymin>
			<xmax>474</xmax>
			<ymax>687</ymax>
		</bndbox>
	</object>
</annotation>
