<annotation>
	<folder>BD2</folder>
	<filename>357.JPG</filename>
	<path>F:\Sieci\BD2\357.JPG</path>
	<source>
		<database>Unknown</database>
	</source>
	<size>
		<width>803</width>
		<height>468</height>
		<depth>3</depth>
	</size>
	<segmented>0</segmented>
	<object>
		<name>shopping_center</name>
		<pose>Unspecified</pose>
		<truncated>0</truncated>
		<difficult>0</difficult>
		<bndbox>
			<xmin>311</xmin>
			<ymin>159</ymin>
			<xmax>574</xmax>
			<ymax>409</ymax>
		</bndbox>
	</object>
	<object>
		<name>block of flats</name>
		<pose>Unspecified</pose>
		<truncated>1</truncated>
		<difficult>0</difficult>
		<bndbox>
			<xmin>1</xmin>
			<ymin>1</ymin>
			<xmax>288</xmax>
			<ymax>91</ymax>
		</bndbox>
	</object>
	<object>
		<name>block of flats</name>
		<pose>Unspecified</pose>
		<truncated>0</truncated>
		<difficult>0</difficult>
		<bndbox>
			<xmin>292</xmin>
			<ymin>26</ymin>
			<xmax>426</xmax>
			<ymax>86</ymax>
		</bndbox>
	</object>
	<object>
		<name>block of flats</name>
		<pose>Unspecified</pose>
		<truncated>1</truncated>
		<difficult>0</difficult>
		<bndbox>
			<xmin>430</xmin>
			<ymin>1</ymin>
			<xmax>606</xmax>
			<ymax>87</ymax>
		</bndbox>
	</object>
	<object>
		<name>block of flats</name>
		<pose>Unspecified</pose>
		<truncated>1</truncated>
		<difficult>0</difficult>
		<bndbox>
			<xmin>648</xmin>
			<ymin>1</ymin>
			<xmax>803</xmax>
			<ymax>84</ymax>
		</bndbox>
	</object>
</annotation>
