<annotation>
	<folder>BD2</folder>
	<filename>389.JPG</filename>
	<path>F:\Sieci\BD2\389.JPG</path>
	<source>
		<database>Unknown</database>
	</source>
	<size>
		<width>490</width>
		<height>777</height>
		<depth>3</depth>
	</size>
	<segmented>0</segmented>
	<object>
		<name>terrace house</name>
		<pose>Unspecified</pose>
		<truncated>1</truncated>
		<difficult>0</difficult>
		<bndbox>
			<xmin>67</xmin>
			<ymin>622</ymin>
			<xmax>473</xmax>
			<ymax>777</ymax>
		</bndbox>
	</object>
	<object>
		<name>terrace house</name>
		<pose>Unspecified</pose>
		<truncated>0</truncated>
		<difficult>0</difficult>
		<bndbox>
			<xmin>61</xmin>
			<ymin>394</ymin>
			<xmax>464</xmax>
			<ymax>539</ymax>
		</bndbox>
	</object>
	<object>
		<name>terrace house</name>
		<pose>Unspecified</pose>
		<truncated>0</truncated>
		<difficult>0</difficult>
		<bndbox>
			<xmin>47</xmin>
			<ymin>16</ymin>
			<xmax>447</xmax>
			<ymax>235</ymax>
		</bndbox>
	</object>
	<object>
		<name>block of flats</name>
		<pose>Unspecified</pose>
		<truncated>0</truncated>
		<difficult>0</difficult>
		<bndbox>
			<xmin>114</xmin>
			<ymin>224</ymin>
			<xmax>263</xmax>
			<ymax>380</ymax>
		</bndbox>
	</object>
</annotation>
